{
  "Name": "C",
  "Flats": [
    {
      "Number": "017",
      "Description": "C017",
      "OwnedBy": "Sandeep A Deshpande",
      "CoOwnedBy": null,
      "TenantName": null,
      "ResidentType": 0,
      "AccountOpenedOn": "2022-09-01T00:00:00",
      "DateSpecified": "2022-09-13T00:00:00+05:30",
      "OpeningBalance": 4600.0,
      "Expenses": null,
      "Payments": [
        {
          "Mode": 1,
          "ReceivedOn": "2022-09-14T00:00:00",
          "Category": 1,
          "Amount": 3000.00
        }
      ],
      "OutstandingOnSpecifiedDate": 4600.0,
      "CurrentOutstanding": 1600.00
    },
    {
      "Number": "018",
      "Description": "C018",
      "OwnedBy": "Rajesh Singh",
      "CoOwnedBy": null,
      "TenantName": null,
      "ResidentType": 0,
      "AccountOpenedOn": "2022-09-01T00:00:00",
      "DateSpecified": "2022-09-13T00:00:00+05:30",
      "OpeningBalance": 2800.0,
      "Expenses": null,
      "Payments": [
        {
          "Mode": 0,
          "ReceivedOn": "2022-09-11T00:00:00",
          "Category": 1,
          "Amount": 2800.00
        }
      ],
      "OutstandingOnSpecifiedDate": 0.00,
      "CurrentOutstanding": 0.00
    },
    {
      "Number": "019",
      "Description": "C019",
      "OwnedBy": "Manjunath",
      "CoOwnedBy": null,
      "TenantName": null,
      "ResidentType": 0,
      "AccountOpenedOn": "2022-09-01T00:00:00",
      "DateSpecified": "2022-09-13T00:00:00+05:30",
      "OpeningBalance": 24240.0,
      "Expenses": null,
      "Payments": null,
      "OutstandingOnSpecifiedDate": 24240.0,
      "CurrentOutstanding": 24240.0
    },
    {
      "Number": "020",
      "Description": "C020",
      "OwnedBy": "B V Nagaraja",
      "CoOwnedBy": null,
      "TenantName": "Manjunath K S",
      "ResidentType": 1,
      "AccountOpenedOn": "2022-09-01T00:00:00",
      "DateSpecified": "2022-09-13T00:00:00+05:30",
      "OpeningBalance": 2800.0,
      "Expenses": null,
      "Payments": [
        {
          "Mode": 0,
          "ReceivedOn": "2022-09-12T00:00:00",
          "Category": 1,
          "Amount": 2800.00
        }
      ],
      "OutstandingOnSpecifiedDate": 0.00,
      "CurrentOutstanding": 0.00
    },
    {
      "Number": "021",
      "Description": "C021",
      "OwnedBy": "Satyanarayana",
      "CoOwnedBy": "Chaya G",
      "TenantName": null,
      "ResidentType": 0,
      "AccountOpenedOn": "2022-09-01T00:00:00",
      "DateSpecified": "2022-09-13T00:00:00+05:30",
      "OpeningBalance": 2800.0,
      "Expenses": null,
      "Payments": [
        {
          "Mode": 0,
          "ReceivedOn": "2022-09-12T00:00:00",
          "Category": 1,
          "Amount": 2800.00
        }
      ],
      "OutstandingOnSpecifiedDate": 0.00,
      "CurrentOutstanding": 0.00
    },
    {
      "Number": "022",
      "Description": "C022",
      "OwnedBy": "Ganapathi M K",
      "CoOwnedBy": null,
      "TenantName": null,
      "ResidentType": 0,
      "AccountOpenedOn": "2022-09-01T00:00:00",
      "DateSpecified": "2022-09-13T00:00:00+05:30",
      "OpeningBalance": 2800.0,
      "Expenses": null,
      "Payments": [
        {
          "Mode": 0,
          "ReceivedOn": "2022-09-12T00:00:00",
          "Category": 1,
          "Amount": 2800.00
        }
      ],
      "OutstandingOnSpecifiedDate": 0.00,
      "CurrentOutstanding": 0.00
    },
    {
      "Number": "023",
      "Description": "C023",
      "OwnedBy": "B V Chandrashekar",
      "CoOwnedBy": null,
      "TenantName": "Raghunath",
      "ResidentType": 1,
      "AccountOpenedOn": "2022-09-01T00:00:00",
      "DateSpecified": "2022-09-13T00:00:00+05:30",
      "OpeningBalance": 15683.0,
      "Expenses": null,
      "Payments": null,
      "OutstandingOnSpecifiedDate": 15683.0,
      "CurrentOutstanding": 15683.0
    },
    {
      "Number": "024",
      "Description": "C024",
      "OwnedBy": "B Mohan Sundaram",
      "CoOwnedBy": "Manika Lakshmi",
      "TenantName": null,
      "ResidentType": 1,
      "AccountOpenedOn": "2022-09-01T00:00:00",
      "DateSpecified": "2022-09-13T00:00:00+05:30",
      "OpeningBalance": 2495.0,
      "Expenses": null,
      "Payments": null,
      "OutstandingOnSpecifiedDate": 2495.0,
      "CurrentOutstanding": 2495.0
    },
    {
      "Number": "117",
      "Description": "C117",
      "OwnedBy": "B V Siddalingaswamy",
      "CoOwnedBy": null,
      "TenantName": null,
      "ResidentType": 1,
      "AccountOpenedOn": "2022-09-01T00:00:00",
      "DateSpecified": "2022-09-13T00:00:00+05:30",
      "OpeningBalance": 16800.0,
      "Expenses": null,
      "Payments": null,
      "OutstandingOnSpecifiedDate": 16800.0,
      "CurrentOutstanding": 16800.0
    },
    {
      "Number": "118",
      "Description": "C118",
      "OwnedBy": "B V Prasad",
      "CoOwnedBy": null,
      "TenantName": "Santhosh",
      "ResidentType": 1,
      "AccountOpenedOn": "2022-09-01T00:00:00",
      "DateSpecified": "2022-09-13T00:00:00+05:30",
      "OpeningBalance": 5600.0,
      "Expenses": null,
      "Payments": [
        {
          "Mode": 0,
          "ReceivedOn": "2022-09-05T00:00:00",
          "Category": 1,
          "Amount": 2800.00
        }
      ],
      "OutstandingOnSpecifiedDate": 2800.00,
      "CurrentOutstanding": 2800.00
    },
    {
      "Number": "119",
      "Description": "C119",
      "OwnedBy": "Gangaiah",
      "CoOwnedBy": "Lalitha M R",
      "TenantName": null,
      "ResidentType": 0,
      "AccountOpenedOn": "2022-09-01T00:00:00",
      "DateSpecified": "2022-09-13T00:00:00+05:30",
      "OpeningBalance": 14000.0,
      "Expenses": null,
      "Payments": null,
      "OutstandingOnSpecifiedDate": 14000.0,
      "CurrentOutstanding": 14000.0
    },
    {
      "Number": "120",
      "Description": "C120",
      "OwnedBy": "Shivanand Chawhan",
      "CoOwnedBy": null,
      "TenantName": null,
      "ResidentType": 0,
      "AccountOpenedOn": "2022-09-01T00:00:00",
      "DateSpecified": "2022-09-13T00:00:00+05:30",
      "OpeningBalance": 5600.0,
      "Expenses": null,
      "Payments": [
        {
          "Mode": 0,
          "ReceivedOn": "2022-09-05T00:00:00",
          "Category": 1,
          "Amount": 2800.00
        },
        {
          "Mode": 1,
          "ReceivedOn": "2022-09-18T00:00:00",
          "Category": 1,
          "Amount": 2800.00
        }
      ],
      "OutstandingOnSpecifiedDate": 2800.00,
      "CurrentOutstanding": 0.00
    },
    {
      "Number": "121",
      "Description": "C121",
      "OwnedBy": "Girish",
      "CoOwnedBy": null,
      "TenantName": null,
      "ResidentType": 0,
      "AccountOpenedOn": "2022-09-01T00:00:00",
      "DateSpecified": "2022-09-13T00:00:00+05:30",
      "OpeningBalance": 2800.0,
      "Expenses": null,
      "Payments": null,
      "OutstandingOnSpecifiedDate": 2800.0,
      "CurrentOutstanding": 2800.0
    },
    {
      "Number": "122",
      "Description": "C122",
      "OwnedBy": "B J Abhishek",
      "CoOwnedBy": "Bharani K",
      "TenantName": null,
      "ResidentType": 0,
      "AccountOpenedOn": "2022-09-01T00:00:00",
      "DateSpecified": "2022-09-13T00:00:00+05:30",
      "OpeningBalance": 2845.0,
      "Expenses": null,
      "Payments": null,
      "OutstandingOnSpecifiedDate": 2845.0,
      "CurrentOutstanding": 2845.0
    },
    {
      "Number": "123",
      "Description": "C123",
      "OwnedBy": "Arun Joshi",
      "CoOwnedBy": null,
      "TenantName": null,
      "ResidentType": 0,
      "AccountOpenedOn": "2022-09-01T00:00:00",
      "DateSpecified": "2022-09-13T00:00:00+05:30",
      "OpeningBalance": 6239.0,
      "Expenses": null,
      "Payments": null,
      "OutstandingOnSpecifiedDate": 6239.0,
      "CurrentOutstanding": 6239.0
    },
    {
      "Number": "124",
      "Description": "C124",
      "OwnedBy": "V S Lokeswarappa",
      "CoOwnedBy": "Manoj L",
      "TenantName": null,
      "ResidentType": 0,
      "AccountOpenedOn": "2022-09-01T00:00:00",
      "DateSpecified": "2022-09-13T00:00:00+05:30",
      "OpeningBalance": 2800.0,
      "Expenses": null,
      "Payments": [
        {
          "Mode": 1,
          "ReceivedOn": "2022-09-16T00:00:00+05:30",
          "Category": 1,
          "Amount": 2800.00
        }
      ],
      "OutstandingOnSpecifiedDate": 2800.0,
      "CurrentOutstanding": 0.00
    },
    {
      "Number": "217",
      "Description": "C217",
      "OwnedBy": "Srinivasa Rao Masanam",
      "CoOwnedBy": null,
      "TenantName": null,
      "ResidentType": 0,
      "AccountOpenedOn": "2022-09-01T00:00:00",
      "DateSpecified": "2022-09-13T00:00:00+05:30",
      "OpeningBalance": 2800.0,
      "Expenses": null,
      "Payments": null,
      "OutstandingOnSpecifiedDate": 2800.0,
      "CurrentOutstanding": 2800.0
    },
    {
      "Number": "218",
      "Description": "C218",
      "OwnedBy": "Laxmikanth Rao",
      "CoOwnedBy": null,
      "TenantName": null,
      "ResidentType": 0,
      "AccountOpenedOn": "2022-09-01T00:00:00",
      "DateSpecified": "2022-09-13T00:00:00+05:30",
      "OpeningBalance": 2800.0,
      "Expenses": null,
      "Payments": null,
      "OutstandingOnSpecifiedDate": 2800.0,
      "CurrentOutstanding": 2800.0
    },
    {
      "Number": "219",
      "Description": "C219",
      "OwnedBy": "Nagendra Murthy M",
      "CoOwnedBy": "Shobha B",
      "TenantName": null,
      "ResidentType": 0,
      "AccountOpenedOn": "2022-09-01T00:00:00",
      "DateSpecified": "2022-09-13T00:00:00+05:30",
      "OpeningBalance": 5600.0,
      "Expenses": null,
      "Payments": null,
      "OutstandingOnSpecifiedDate": 5600.0,
      "CurrentOutstanding": 5600.0
    },
    {
      "Number": "220",
      "Description": "C220",
      "OwnedBy": "Somala M",
      "CoOwnedBy": "Gopal N",
      "TenantName": null,
      "ResidentType": 0,
      "AccountOpenedOn": "2022-09-01T00:00:00",
      "DateSpecified": "2022-09-13T00:00:00+05:30",
      "OpeningBalance": 20100.0,
      "Expenses": null,
      "Payments": null,
      "OutstandingOnSpecifiedDate": 20100.0,
      "CurrentOutstanding": 20100.0
    },
    {
      "Number": "221",
      "Description": "C221",
      "OwnedBy": "Bhavani",
      "CoOwnedBy": "Ravi Prakash",
      "TenantName": null,
      "ResidentType": 0,
      "AccountOpenedOn": "2022-09-01T00:00:00",
      "DateSpecified": "2022-09-13T00:00:00+05:30",
      "OpeningBalance": 2800.0,
      "Expenses": null,
      "Payments": [
        {
          "Mode": 1,
          "ReceivedOn": "2022-09-14T00:00:00",
          "Category": 1,
          "Amount": 2800.00
        }
      ],
      "OutstandingOnSpecifiedDate": 2800.0,
      "CurrentOutstanding": 0.00
    },
    {
      "Number": "222",
      "Description": "C222",
      "OwnedBy": "B V Chandrashekar",
      "CoOwnedBy": null,
      "TenantName": "Harish",
      "ResidentType": 1,
      "AccountOpenedOn": "2022-09-01T00:00:00",
      "DateSpecified": "2022-09-13T00:00:00+05:30",
      "OpeningBalance": 5600.0,
      "Expenses": null,
      "Payments": null,
      "OutstandingOnSpecifiedDate": 5600.0,
      "CurrentOutstanding": 5600.0
    },
    {
      "Number": "223",
      "Description": "C223",
      "OwnedBy": "Praveen Gouda Patil",
      "CoOwnedBy": null,
      "TenantName": null,
      "ResidentType": 0,
      "AccountOpenedOn": "2022-09-01T00:00:00",
      "DateSpecified": "2022-09-21T00:00:00",
      "OpeningBalance": 1400.0,
      "Expenses": null,
      "Payments": [
        {
          "Mode": 1,
          "ReceivedOn": "2022-09-14T00:00:00",
          "Category": 1,
          "Amount": 1400.00
        }
      ],
      "OutstandingOnSpecifiedDate": 0.00,
      "CurrentOutstanding": 0.00
    },
    {
      "Number": "224",
      "Description": "C224",
      "OwnedBy": "Pradeepa K S",
      "CoOwnedBy": "Vaishnavi G R",
      "TenantName": null,
      "ResidentType": 0,
      "AccountOpenedOn": "2022-09-01T00:00:00",
      "DateSpecified": "2022-09-13T00:00:00+05:30",
      "OpeningBalance": 2800.0,
      "Expenses": null,
      "Payments": [
        {
          "Mode": 1,
          "ReceivedOn": "2022-09-15T00:00:00",
          "Category": 1,
          "Amount": 2800.00
        }
      ],
      "OutstandingOnSpecifiedDate": 2800.0,
      "CurrentOutstanding": 0.00
    },
    {
      "Number": "317",
      "Description": "C317",
      "OwnedBy": "Santosh Kumar P",
      "CoOwnedBy": "Ashwini Krishnappa",
      "TenantName": null,
      "ResidentType": 0,
      "AccountOpenedOn": "2022-09-01T00:00:00",
      "DateSpecified": "2022-09-13T00:00:00+05:30",
      "OpeningBalance": 0.0,
      "Expenses": null,
      "Payments": null,
      "OutstandingOnSpecifiedDate": 0.0,
      "CurrentOutstanding": 0.0
    },
    {
      "Number": "318",
      "Description": "C318",
      "OwnedBy": "B V Chandrashekar",
      "CoOwnedBy": null,
      "TenantName": null,
      "ResidentType": 1,
      "AccountOpenedOn": "2022-09-01T00:00:00",
      "DateSpecified": "2022-09-13T00:00:00+05:30",
      "OpeningBalance": 16800.0,
      "Expenses": null,
      "Payments": null,
      "OutstandingOnSpecifiedDate": 16800.0,
      "CurrentOutstanding": 16800.0
    },
    {
      "Number": "319",
      "Description": "C319",
      "OwnedBy": "M G Harish Babu",
      "CoOwnedBy": null,
      "TenantName": null,
      "ResidentType": 0,
      "AccountOpenedOn": "2022-09-01T00:00:00",
      "DateSpecified": "2022-09-13T00:00:00+05:30",
      "OpeningBalance": 18240.0,
      "Expenses": null,
      "Payments": null,
      "OutstandingOnSpecifiedDate": 18240.0,
      "CurrentOutstanding": 18240.0
    },
    {
      "Number": "320",
      "Description": "C320",
      "OwnedBy": "Shrikanth MH",
      "CoOwnedBy": "Jyothi HC",
      "TenantName": null,
      "ResidentType": 0,
      "AccountOpenedOn": "2022-09-01T00:00:00",
      "DateSpecified": "2022-09-13T00:00:00+05:30",
      "OpeningBalance": 2800.0,
      "Expenses": null,
      "Payments": [
        {
          "Mode": 0,
          "ReceivedOn": "2022-09-13T00:00:00",
          "Category": 1,
          "Amount": 2800.00
        }
      ],
      "OutstandingOnSpecifiedDate": 0.00,
      "CurrentOutstanding": 0.00
    },
    {
      "Number": "321",
      "Description": "C321",
      "OwnedBy": "Santosh P",
      "CoOwnedBy": "Nithya B",
      "TenantName": null,
      "ResidentType": 0,
      "AccountOpenedOn": "2022-09-01T00:00:00",
      "DateSpecified": "2022-09-13T00:00:00+05:30",
      "OpeningBalance": 40385.0,
      "Expenses": null,
      "Payments": null,
      "OutstandingOnSpecifiedDate": 40385.0,
      "CurrentOutstanding": 40385.0
    },
    {
      "Number": "322",
      "Description": "C322",
      "OwnedBy": "Sai Shravanth",
      "CoOwnedBy": null,
      "TenantName": null,
      "ResidentType": 0,
      "AccountOpenedOn": "2022-09-01T00:00:00",
      "DateSpecified": "2022-09-13T00:00:00+05:30",
      "OpeningBalance": 2800.0,
      "Expenses": null,
      "Payments": null,
      "OutstandingOnSpecifiedDate": 2800.0,
      "CurrentOutstanding": 2800.0
    },
    {
      "Number": "323",
      "Description": "C323",
      "OwnedBy": "Nikhil Kulkarni",
      "CoOwnedBy": null,
      "TenantName": null,
      "ResidentType": 0,
      "AccountOpenedOn": "2022-09-01T00:00:00",
      "DateSpecified": "2022-09-13T00:00:00+05:30",
      "OpeningBalance": 21490.0,
      "Expenses": null,
      "Payments": [
        {
          "Mode": 0,
          "ReceivedOn": "2022-09-05T00:00:00",
          "Category": 1,
          "Amount": 2800.00
        }
      ],
      "OutstandingOnSpecifiedDate": 18690.00,
      "CurrentOutstanding": 18690.00
    },
    {
      "Number": "324",
      "Description": "C324",
      "OwnedBy": "B V Nagaraja",
      "CoOwnedBy": "Deepa BN",
      "TenantName": null,
      "ResidentType": 0,
      "AccountOpenedOn": "2022-09-01T00:00:00",
      "DateSpecified": "2022-09-13T00:00:00+05:30",
      "OpeningBalance": 2600.0,
      "Expenses": null,
      "Payments": null,
      "OutstandingOnSpecifiedDate": 2600.0,
      "CurrentOutstanding": 2600.0
    }
  ]
}